minillm/__init__.py
minillm/config.py
minillm/embeddings.py
minillm/inference.py
minillm/models.py
minillm-2.1.dist-info/METADATA
minillm-2.1.dist-info/WHEEL
minillm-2.1.dist-info/top_level.txt
minillm-2.1.dist-info/RECORD
