Metadata-Version: 2.1
Name: minillm
Version: 2.1
Summary: Simple inference for large language models
Home-page: https://github.com/IMApurbo/minillm
Author: AKM Korishee Apurbo
Author-email: bandinvisible8@gmail.com
Classifier: Programming Language :: Python :: 3
Classifier: License :: OSI Approved :: MIT License
Classifier: Operating System :: OS Independent
Requires-Python: >=3.8
Requires-Dist: huggingface-hub
Requires-Dist: ctranslate2 >=4.4.0
Requires-Dist: tokenizers
